extraredis/__init__.py
extraredis/base.py
extraredis/util.py
extraredis/_async/__init__.py
extraredis/_sync/__init__.py
extraredis-0.1.0.dist-info/METADATA
extraredis-0.1.0.dist-info/WHEEL
extraredis-0.1.0.dist-info/top_level.txt
extraredis-0.1.0.dist-info/RECORD
