Metadata-Version: 2.1
Name: extraredis
Version: 0.1.0
Summary: extra methods for redis
Home-page: https://gitea.tandav.me/tandav/extraredis
Author: Alexander Rodionov
Author-email: tandav@tandav.me
Requires-Python: >=3.8
Requires-Dist: redis[hiredis]
Provides-Extra: dev
Requires-Dist: bumpver ; extra == 'dev'
Requires-Dist: pre-commit ; extra == 'dev'
Requires-Dist: pytest ; extra == 'dev'
Requires-Dist: fakeredis ; extra == 'dev'
Requires-Dist: pytest-asyncio ; extra == 'dev'
Requires-Dist: python-dotenv ; extra == 'dev'
